bootstrap/__init__.py
bootstrap/__main__.py
bootstrap/bootstrap.py
ansible_lint_nunit-0.5.dist-info/LICENSE.txt
ansible_lint_nunit-0.5.dist-info/METADATA
ansible_lint_nunit-0.5.dist-info/WHEEL
ansible_lint_nunit-0.5.dist-info/entry_points.txt
ansible_lint_nunit-0.5.dist-info/top_level.txt
ansible_lint_nunit-0.5.dist-info/RECORD
