Metadata-Version: 2.1
Name: ansible-lint-nunit
Version: 0.5
Summary: ansible-lint to NUnit converter.
Home-page: https://github.com/ferhaty/ansible-lint-nunit
Author: ferhaty
Author-email: ferhat.yildiz@turingts.com
License: UNKNOWN
Download-URL: https://github.com/ferhaty/ansible-lint-nunit/archive/0.5.tar.gz
Keywords: ansible,nunit
Platform: UNKNOWN
Requires-Dist: ansible-lint
